Workbook

Sheet Config
B2: ⚙️ CONFIGURACIÓN DEL PROYECTO
B3: Edita las celdas en amarillo → todo el reporte se actualiza automáticamente
B5: Nombre del Proyecto | C5: Proyecto Papa 2025-2026
B7: Total de Hectáreas | C7: 90
B9: Área a Excluir del Reporte | C9: Inversiones
B12: 💡 Celdas en amarillo = editables. Cambia el nombre del proyecto, hectáreas o el área a excluir y todas las hojas se recalcularán automáticamente.
B14: ÁREAS A INCLUIR EN EL REPORTE (actualiza si cambian los nombres)
B15: Nombre del Área | C15: Administracion
B16: Nombre del Área | C16: Operación
B18: 📋 INSTRUCCIONES PARA NUEVO PROYECTO: 1) Reemplaza los datos en la hoja "Datos" 2) Actualiza Categorías en "🗂️ Por Categoría" 3) Cambia los valores amarillos aquí y el reporte se actualiza solo

Sheet Datos
A1: Area | B1: Clasificacion | C1: Fecha | D1: Proveedor | E1: Concepto | F1: Importe | G1: Pago | H1: Pendiente
A2: Operación | B2: Yarda | C2: 13/01/2026 | D2: YARDA | E2: DIESEL YARDA | F2: 188761.59 | G2: 188761.59 | H2: =MAX(F2-G2,0) -> 0
A3: Operación | B3: Yarda | C3: 13/03/2026 | D3: YARDA | E3: DIESEL YARDA | F3: 296648.6 | G3: 296648.6 | H3: =MAX(F3-G3,0) -> 0
A4: Operación | B4: Yarda | C4: 16/10/2025 | D4: YARDA | E4: DIESEL YARDA | F4: 248711.93 | G4: 248711.93 | H4: =MAX(F4-G4,0) -> 0
A5: Operación | B5: Yarda | C5: 18/08/2025 | D5: YARDA | E5: DIESEL YARDA | F5: 277829.1 | G5: 277829.1 | H5: =MAX(F5-G5,0) -> 0
A6: Administracion | B6: Finiquito | C6: 08/12/2025 | D6: Xitlali Marisela | E6: Finiquito | F6: 9543.32 | G6: 9543.32 | H6: =MAX(F6-G6,0) -> 0
A7: Administracion | B7: Nomina Administrativa | C7: 13/06/2025 | D7: Xitlali Marisela | E7: Nomina Quincenal | F7: 4240.55 | G7: 4240.55 | H7: =MAX(F7-G7,0) -> 0
A8: Administracion | B8: Nomina Administrativa | C8: 14/10/2025 | D8: Xitlali Marisela | E8: Nomina Quincenal | F8: 4240.55 | G8: 4240.55 | H8: =MAX(F8-G8,0) -> 0
A9: Administracion | B9: Nomina Administrativa | C9: 15/07/2025 | D9: Xitlali Marisela | E9: Nomina Quincenal | F9: 4240.55 | G9: 4240.55 | H9: =MAX(F9-G9,0) -> 0
A10: Administracion | B10: Nomina Administrativa | C10: 15/08/2025 | D10: Xitlali Marisela | E10: Nomina Quincenal | F10: 4240.55 | G10: 4240.55 | H10: =MAX(F10-G10,0) -> 0
A11: Administracion | B11: Nomina Administrativa | C11: 15/09/2025 | D11: Xitlali Marisela | E11: Nomina Quincenal | F11: 4240.55 | G11: =+Datos!$F11 -> 4240.55 | H11: =MAX(F11-G11,0) -> 0
A12: Administracion | B12: Nomina Administrativa | C12: 15/10/2025 | D12: Xitlali Marisela | E12: Nomina Quincenal | F12: 4240.55 | G12: 4240.55 | H12: =MAX(F12-G12,0) -> 0
A13: Administracion | B13: Nomina Administrativa | C13: 28/10/2025 | D13: Xitlali Marisela | E13: Nomina Quincenal | F13: 4240.55 | G13: 4240.55 | H13: =MAX(F13-G13,0) -> 0
A14: Administracion | B14: Nomina Administrativa | C14: 29/08/2025 | D14: Xitlali Marisela | E14: Nomina Quincenal | F14: 4240.55 | G14: 4240.55 | H14: =MAX(F14-G14,0) -> 0
A15: Administracion | B15: Nomina Administrativa | C15: 30/06/2025 | D15: Xitlali Marisela | E15: Nomina Quincenal | F15: 4240.55 | G15: 4240.55 | H15: =MAX(F15-G15,0) -> 0
A16: Administracion | B16: Nomina Administrativa | C16: 30/09/2025 | D16: Xitlali Marisela | E16: Nomina Quincenal | F16: 4240.55 | G16: 4240.55 | H16: =MAX(F16-G16,0) -> 0
A17: Administracion | B17: Nomina Administrativa | C17: 31/07/2025 | D17: Xitlali Marisela | E17: Nomina Quincenal | F17: 4240.55 | G17: 4240.55 | H17: =MAX(F17-G17,0) -> 0
A18: Administracion | B18: Nomina Administrativa | C18: 31/10/2025 | D18: Xitlali Marisela | E18: Nomina Quincenal | F18: 4240.55 | G18: 4240.55 | H18: =MAX(F18-G18,0) -> 0
A19: Operación | B19: Cuadrillas Siembra | C19: 07/11/2025 | D19: Xeloma | E19: Cuadrilla Conexciones 45 | F19: 25400 | G19: 25400 | H19: =MAX(F19-G19,0) -> 0
A20: Administracion | B20: Uniformes | C20: 25/09/2025 | D20: VICTOR ROCHA RUIZ | E20: BORDADO BASICO (1-5) | F20: 99.9 | G20: 99.9 | H20: =MAX(F20-G20,0) -> 0
A21: Administracion | B21: Uniformes | C21: 26/08/2025 | D21: VICTOR ROCHA RUIZ | E21: BORDADO BASICO (6-X) | F21: 350.09 | G21: 350.09 | H21: =MAX(F21-G21,0) -> 0
A22: Operación | B22: Yarda | C22: 18/04/2026 | D22: VBT | E22: DIESEL YARDA | F22: 89203.9 | G22: 89203.9 | H22: =MAX(F22-G22,0) -> 0
A23: Inversiones | B23: Reservorio | C23: 28/07/2025 | D23: ERIC ABRAHAM HERNANDEZ RUBIO | E23: SISTEMA DE RIEGO AGRICOLA | F23: 998386 | G23: 798708.8 | H23: =MAX(F23-G23,0) -> 199677.2
... A102: Operación | B102: Fertilizantes y Agroquimicos | C102: 27/12/2025 | D102: SERVICIOS Y FERTILIZANTES DEL NOROESTE | E102: SERENATE ASO | F102: 30780 | G102: 30780 | H102: =MAX(F102-G102,0) -> 0
A103: Operación | B103: Fertilizantes y Agroquimicos | C103: 30/03/2026 | D103: SERVICIOS Y FERTILIZANTES DEL NOROESTE | E103: "12 METONATE 5 DAR PLUS 5 PUSH " | F103: 10806 | G103: =+Datos!$F103 -> 10806 | H103: =MAX(F103-G103,0) -> 0
A104: Operación | B104: Gasolina | C104: 27/10/2025 | D104: SERVICIOS VILLA JUAREZ | E104: REGULAR | F104: 100 | G104: 100 | H104: =MAX(F104-G104,0) -> 0
A105: Administracion | B105: Gastos de Oficina | C105: 02/10/2025 | D105: SERVICIOS OPERATIVOS LOGISTICOS DE CAJEM | E105: SUBARRENDAMIENTO DE LOCAL PARA OFICINA OCTUBRE 2025 | F105: 5504.2 | G105: 5504.2 | H105: =MAX(F105-G105,0) -> 0
A106: Administracion | B106: Gastos de Oficina | C106: 04/08/2025 | D106: SERVICIOS OPERATIVOS LOGISTICOS DE CAJEM | E106: SUBARRENDAMIENTO DE LOCAL PARA OFICINA AGOSTO 2025 | F106: 5504.2 | G106: 5504.2 | H106: =MAX(F106-G106,0) -> 0
A107: Administracion | B107: Gastos de Oficina | C107: 04/09/2025 | D107: SERVICIOS OPERATIVOS LOGISTICOS DE CAJEM | E107: SUBARRENDAMIENTO DE LOCAL PARA OFICINA SEPTIEMBRE 2025 | F107: 5504.2 | G107: 5504.2 | H107: =MAX(F107-G107,0) -> 0
A108: Administracion | B108: Gastos de Oficina | C108: 04/12/2025 | D108: SERVICIOS OPERATIVOS LOGISTICOS DE CAJEM | E108: SUBARRENDAMIENTO DE LOCAL PARA OFICINA DICIEMBRE 2025 | F108: 5504.2 | G108: 5504.2 | H108: =MAX(F108-G108,0) -> 0
A109: Administracion | B109: Gastos de Oficina | C109: 05/06/2025 | D109: SERVICIOS OPERATIVOS LOGISTICOS DE CAJEM | E109: SUBARRENDAMIENTO DE LOCAL PARA OFICINA JUNIO 2025 | F109: 5504.2 | G109: 5504.2 | H109: =MAX(F109-G109,0) -> 0
A110: Administracion | B110: Gastos de Oficina | C110: 07/11/2025 | D110: SERVICIOS OPERATIVOS LOGISTICOS DE CAJEM | E110: SEBARRENDAMIENTO DE LOCAL PARA OFICINA NOV 2025 | F110: 5504.2 | G110: 5504.2 | H110: =MAX(F110-G110,0) -> 0
A111: Operación | B111: Gasolina | C111: 09/03/2026 | D111: SERVICIO JECOPACO | E111: 20,833 LT MAGNA | F111: 500 | G111: 500 | H111: =MAX(F111-G111,0) -> 0
A112: Operación | B112: Gasolina | C112: 14/02/2026 | D112: SERVICIO JECOPACO | E112: 8,333 LT MAGNA | F112: 200 | G112: 200 | H112: =MAX(F112-G112,0) -> 0
A113: Operación | B113: Gasolina | C113: 16/02/2026 | D113: SERVICIO JECOPACO | E113: 8,336 LT REGULAR | F113: 200.06 | G113: 200.06 | H113: =MAX(F113-G113,0) -> 0
A114: Operación | B114: Gasolina | C114: 16/03/2026 | D114: SERVICIO JECOPACO | E114: 8,333 LT REGULAR | F114: 200 | G114: 200 | H114: =MAX(F114-G114,0) -> 0
A115: Operación | B115: Gasolina | C115: 17/02/2026 | D115: SERVICIO JECOPACO | E115: 8,333 LT REGULAR | F115: 200 | G115: 200 | H115: =MAX(F115-G115,0) -> 0
... A274: Administracion | B274: Nomina Administrativa | C274: 31/07/2025 | D274: Michelle Villegas | E274: Nomina Quincenal | F274: 4182 | G274: 4182 | H274: =MAX(F274-G274,0) -> 0
A275: Operación | B275: Analisis | C275: 02/09/2025 | D275: MARIA DEL ROSARIO ZAMORA PEÑA | E275: ANALISIS DE FERTILIDAD FOL. LAB. 32,376 AL 32,379 ANALISIS DE EXTRACTO SATURADO
A276: Operación | B276: Analisis | C276: 03/10/2025 | D276: MARIA DEL ROSARIO ZAMORA PEÑA | E276: ANALISIS DE FERTILIDAD FOL. LAB. 32, 587 AL 32,590 ANALISIS DE EXTRACTO SATURADO
A277: Operación | B277: Analisis | C277: 24/09/2025 | D277: MARIA DEL ROSARIO ZAMORA PEÑA | E277: ANALISIS DE FERTILIDAD FOL ANALISIS DE EXTRACTO SATURADO FOL LAB
A278: Operación | B278: Analisis | C278: 30/10/2025 | D278: MARIA DEL ROSARIO ZAMORA PEÑA | E278: ANALISIS DE AGUA FOL. LAB 8483
A279: Operación | B279: Refacciones Maquinaria | C279: 05/03/2026 | D279: MAQUINARIA PARA PAPAS BLANCHET | E279: CHUMACERA PARED | F279: 4953.74 | G279: =+Datos!$F279 -> 4953.74 | H279: =MAX(F279-G279,0) -> 0
A280: Operación | B280: Refacciones Maquinaria | C280: 19/11/2025 | D280: MAQUINARIA PARA PAPAS BLANCHET | E280: CHUMACERA PARED 4 BARRENOS 2" 1/4" BROWING | F280: 7207.03 | G280: 7207.03 | H280: =MAX(F280-G280,0) -> 0
A281: Operación | B281: Refacciones Maquinaria | C281: 26/03/2026 | D281: MAQUINARIA PARA PAPAS BLANCHET | E281: CATARINA 60-14 | F281: 763.28 | G281: =+Datos!$F281 -> 763.28 | H281: =MAX(F281-G281,0) -> 0
A282: Operación | B282: Refacciones Maquinaria | C282: 04/03/2026 | D282: LUIS DURAN AVALOS | E282: REPARACIÓN DE MAQUINA COSECHADORA DE PAPA | F282: 5800 | G282: 5800 | H282: =MAX(F282-G282,0) -> 0
A283: Operación | B283: Refacciones Maquinaria | C283: 01/12/2025 | D283: LUIS DURAN AVALOS | E283: CAMBIO DE CHUMACERAS A ROTATIL | F283: 5220 | G283: 5220 | H283: =MAX(F283-G283,0) -> 0
A284: Operación | B284: Refacciones Maquinaria | C284: 05/06/2025 | D284: Luis Duran Avalos | E284: CAMBIO DE CHUMACERA A DOS MAQUINAS CORRUGADORAS DE PAPA | F284: 9280 | G284: 9280 | H284: =MAX(F284-G284,0) -> 0
A285: Operación | B285: Refacciones Maquinaria | C285: 05/06/2025 | D285: Luis Duran Avalos | E285: FABRICACION DE ANGULOS (3) TORNILLOS Y MANO DE OBRA FABRICACION DE 9 ZAPATOS PAR | F285: 14732 | G285: 14732 | H285: =MAX(F285-G285,0) -> 0
A286: Operación | B286: Refacciones Maquinaria | C286: 12/11/2025 | D286: LUIS DURAN AVALOS | E286: CAMBIO DE CHUMACERAS A ROTAIL | F286: 5220 | G286: 5220 | H286: =MAX(F286-G286,0) -> 0
A287: Operación | B287: Refacciones Maquinaria | C287: 13/02/2026 | D287: LUIS ALVAREZ E HIJOS | E287: 44,46 LT REGULAR BARDAHL F-1 SINTETICO GASOLINA 5W30 SQ 946 ML | F287: 1182 | G287: 1182 | H287: =MAX(F287-G287,0) -> 0
A288: Operación | B288: Fertilizantes y Agroquimicos | C288: 02/01/2026 | D288: LUIS ALFONSO KNAPP NAVARRO | E288: 19 PORROS ACUAGRO MG 20 LT | F288: 19380 | G288: 0 | H288: =MAX(F288-G288,0) -> 19380
A289: Operación | B289: Fertilizantes y Agroquimicos | C289: 03/11/2025 | D289: LUIS ALFONSO KNAPP NAVARRO | E289: ACUA SUELO SALZ ACUAGRO ACUA SUELO PHD | F289: 21360 | G289: 21630 | H289: =MAX(F289-G289,0) -> 0
A290: Operación | B290: Fertilizantes y Agroquimicos | C290: 07/02/2026 | D290: LUIS ALFONSO KNAPP NAVARRO | E290: 15 ACUAGRO K (POTASIO 20LT) | F290: 22500 | G290: 0 | H290: =MAX(F290-G290,0) -> 22500
A291: Operación | B291: Fertilizantes y Agroquimicos | C291: 09/02/2026 | D291: LUIS ALFONSO KNAPP NAVARRO | E291: 10 ACUAGRO CALCIO+PLUS (20LT) | F291: 15000 | G291: 0 | H291: =MAX(F291-G291,0) -> 15000
A292: Operación | B292: Fertilizantes y Agroquimicos | C292: 09/12/2025 | D292: LUIS ALFONSO KNAPP NAVARRO | E292: 6 PHD 20 LT 8 AZUFRE 20 LT 8 SALZ 20 LT | F292: 27720 | G292: 0 | H292: =MAX(F292-G292,0) -> 27720
A293: Operación | B293: Fertilizantes y Agroquimicos | C293: 09/12/2025 | D293: LUIS ALFONSO KNAPP NAVARRO | E293: 4 PHD 20 LT | F293: 6000 | G293: 0 | H293: =MAX(F293-G293,0) -> 6000
... A304: Operación | B304: Fertilizantes y Agroquimicos | C304: 20/10/2025 | D304: LUIS ALFONSO KNAPP NAVARRO | E304: ACUAGRO 8-24-00 | F304: 17520 | G304: 17520 | H304: =MAX(F304-G304,0) -> 0
A305: Operación | B305: Fertilizantes y Agroquimicos | C305: 22/10/2025 | D305: LUIS ALFONSO KNAPP NAVARRO | E305: MEZCLA PLAA 12-16-18 | F305: 451050 | G305: =+Datos!$F305 -> 451050 | H305: =MAX(F305-G305,0) -> 0
A306: Operación | B306: Fertilizantes y Agroquimicos | C306: 22/12/2025 | D306: LUIS ALFONSO KNAPP NAVARRO | E306: nan | F306: 70000 | G306: 0 | H306: =MAX(F306-G306,0) -> 70000
A307: Operación | B307: Fertilizantes y Agroquimicos | C307: 23/12/2025 | D307: LUIS ALFONSO KNAPP NAVARRO | E307: 1 TÓTEM ACUAGRO K | F307: 71000 | G307: 0 | H307: =MAX(F307-G307,0) -> 71000
A308: Operación | B308: Fertilizantes y Agroquimicos | C308: 24/11/2025 | D308: LUIS ALFONSO KNAPP NAVARRO | E308: ACUAGRO CALCIO PLUS | F308: 24000 | G308: 0 | H308: =MAX(F308-G308,0) -> 24000
A309: Operación | B309: Fertilizantes y Agroquimicos | C309: 24/11/2025 | D309: LUIS ALFONSO KNAPP NAVARRO | E309: NITRATO DE CALCIO | F309: 4355 | G309: 0 | H309: =MAX(F309-G309,0) -> 4355
A310: Operación | B310: Fertilizantes y Agroquimicos | C310: 25/10/2025 | D310: LUIS ALFONSO KNAPP NAVARRO | E310: MEZCLA PLATA 13-15-18+3S+10S04+2.03 MG +1.08 | F310: 634725 | G310: =+Datos!$F310 -> 634725 | H310: =MAX(F310-G310,0) -> 0
A311: Operación | B311: Fertilizantes y Agroquimicos | C311: 27/10/2025 | D311: LUIS ALFONSO KNAPP NAVARRO | E311: ACUA-SUELO SALZ (20 LT) ACUAGRO - S (20 LT) (AZUFRE) ACUA-SUELO PHD | F311: 20040 | G311: =+Datos!$F311 -> 20040 | H311: =MAX(F311-G311,0) -> 0
A312: Operación | B312: Fertilizantes y Agroquimicos | C312: 27/10/2025 | D312: LUIS ALFONSO KNAPP NAVARRO | E312: ACUAGRO - S (20 LT) (AZUFRE) | F312: 7300 | G312: =+Datos!$F312 -> 7300 | H312: =MAX(F312-G312,0) -> 0
A313: Operación | B313: Fertilizantes y Agroquimicos | C313: 27/11/2025 | D313: LUIS ALFONSO KNAPP NAVARRO | E313: (23 DE 25 KG) NITRATO DE CALCIO | F313: 4255 | G313: 0 | H313: =MAX(F313-G313,0) -> 4255
A314: Operación | B314: Fertilizantes y Agroquimicos | C314: 28/01/2026 | D314: LUIS ALFONSO KNAPP NAVARRO | E314: nan | F314: 28500 | G314: 0 | H314: =MAX(F314-G314,0) -> 28500
A315: Operación | B315: Fertilizantes y Agroquimicos | C315: 29/10/2025 | D315: LUIS ALFONSO KNAPP NAVARRO | E315: ACUAGRO 8-24-00 | F315: 69000 | G315: =+Datos!$F315 -> 69000 | H315: =MAX(F315-G315,0) -> 0
A316: Operación | B316: Fertilizantes y Agroquimicos | C316: 29/11/2025 | D316: LUIS ALFONSO KNAPP NAVARRO | E316: (TOTEM) ACUAGRO 8-24-00 | F316: 69000 | G316: 0 | H316: =MAX(F316-G316,0) -> 69000
A317: Operación | B317: Fertilizantes y Agroquimicos | C317: 30/01/2026 | D317: LUIS ALFONSO KNAPP NAVARRO | E317: nan | F317: 21000 | G317: 0 | H317: =MAX(F317-G317,0) -> 21000
A318: Operación | B318: Fertilizantes y Agroquimicos | C318: 31/12/2025 | D318: LUIS ALFONSO KNAPP NAVARRO | E318: 12 PORROS ACASUELO SALZ 20 LT 5 PRROS ACASUELO PHD 20 LT | F318: 25500 | G318: 0 | H318: =MAX(F318-G318,0) -> 25500
A319: Operación | B319: Refacciones y Servicios Vehiculos | C319: 23/07/2025 | D319: LUBRIFILTROS | E319: BG ENGINE KIT BG 245 PREMIUM DIESEL FUEL SYSTEM BG PLATINUM 44 K | F319: 5946.97 | G319: 5946.97 | H319: =MAX(F319-G319,0) -> 0
A320: Operación | B320: Refacciones Maquinaria | C320: 08/09/2025 | D320: LJB FERRETERA INDUSTRIAL DE CAJEME | E320: LUBRICANTE LIMPIADOR DE FRENOS LUBRICANTE BARDHAL ACEITE SILICON TARRO CEPILLO | F320: 1516.4 | G320: 1516.4 | H320: =MAX(F320-G320,0) -> 0
A321: Operación | B321: Refacciones Maquinaria | C321: 10/10/2025 | D321: LJB FERRETERA INDUSTRIAL DE CAJEME | E321: ARE CHUMACERA TROQ | F321: 1740 | G321: 1740 | H321: =MAX(F321-G321,0) -> 0
A322: Operación | B322: Refacciones y Servicios Vehiculos | C322: 13/03/2026 | D322: JULIO CESAR ENCINAS CORDOVA | E322: ACUMULADOR LTH | F322: 2800.01 | G322: 2800.01 | H322: =MAX(F322-G322,0) -> 0
A323: Operación | B323: Refacciones y Servicios Vehiculos | C323: 29/10/2025 | D323: JULIO CESAR ENCINAS CORDOVA | E323: ACUMULADOR LTH | F323: 3100 | G323: 3100 | H323: =MAX(F323-G323,0) -> 0
A324: Administracion | B324: Gastos de Oficina | C324: 02/08/2025 | D324: JUAN PEDRO HURTADO GOMEZ | E324: MONITOREO DEL MES DE AGOSTO 2025 | F324: 550 | G324: 550 | H324: =MAX(F324-G324,0) -> 0
A325: Administracion | B325: Gastos de Oficina | C325: 02/09/2025 | D325: JUAN PEDRO HURTADO GOMEZ | E325: MONITOREO DEL MES DE SEPT | F325: 550 | G325: 550 | H325: =MAX(F325-G325,0) -> 0
A326: Administracion | B326: Gastos de Oficina | C326: 02/10/2025 | D326: JUAN PEDRO HURTADO GOMEZ | E326: MONITOREO DEL MES DE OCTUBRE 2025 | F326: 550 | G326: 550 | H326: =MAX(F326-G326,0) -> 0
A327: Administracion | B327: Gastos de Oficina | C327: 02/12/2025 | D327: JUAN PEDRO HURTADO GOMEZ | E327: MONITOREO DEL MES DE DIC 2025 | F327: 550 | G327: 550 | H327: =MAX(F327-G327,0) -> 0
... A333: Operación | B333: Refacciones y Servicios Vehiculos | C333: 17/06/2025 | D333: JOSE SERGIO GIL SAMANIEGO GUTIERREZ | E333: MANO DE OBRA | F333: 803.25 | G333: 803.25 | H333: =MAX(F333-G333,0) -> 0
A334: Administracion | B334: Honorarios | C334: 46015 | D334: JOSE RUBEN GUTIERREZ MENDOZA | E334: HONORARIOS CONTABLES
A335: Administracion | B335: Honorarios | C335: 22/10/2025 | D335: JOSE RUBEN GUTIERREZ MENDOZA | E335: HONORARIOS CONTABLES
A336: Administracion | B336: Honorarios | C336: 24/08/2025 | D336: JOSE RUBEN GUTIERREZ MENDOZA | E336: HONORARIOS CONTABLES
A337: Administracion | B337: Honorarios | C337: 24/11/2025 | D337: JOSE RUBEN GUTIERREZ MENDOZA | E337: HONORARIOS CONTABLES
A338: Administracion | B338: Honorarios | C338: 27/09/2025 | D338: JOSE RUBEN GUTIERREZ MENDOZA | E338: HONORARIOS CONTABLES
A339: Administracion | B339: Honorarios | C339: 45864 | D339: JOSE RUBEN GUTIERREZ MENDOZA | E339: HONORARIOS CONTABLES | F339: 25000.01 | G339: 25000.01 | H339: =MAX(F339-G339,0) -> 0
A340: Operación | B340: Nomina Operativa | C340: 06/03/2026 | D340: Jose Luis | E340: Nomina Semanal 10 | F340: 3860 | G340: 3860 | H340: =MAX(F340-G340,0) -> 0
A341: Operación | B341: Nomina Operativa | C341: 13/03/2026 | D341: Jose Luis | E341: Nomina Semanal 11 | F341: 3860 | G341: 3860 | H341: =MAX(F341-G341,0) -> 0
A342: Operación | B342: Nomina Operativa | C342: 20/02/2026 | D342: Jose Luis | E342: Nomina Semanal 08 | F342: 2400 | G342: 2400 | H342: =MAX(F342-G342,0) -> 0
A343: Operación | B343: Nomina Operativa | C343: 20/03/2026 | D343: Jose Luis | E343: Nomina Semanal 12 | F343: 3860 | G343: 3860 | H343: =MAX(F343-G343,0) -> 0
A344: Operación | B344: Nomina Operativa | C344: 27/02/2026 | D344: Jose Luis | E344: Nomina Semanal 09 | F344: 3360 | G344: 3360 | H344: =MAX(F344-G344,0) -> 0
A345: Operación | B345: Nomina Operativa | C345: 27/03/2026 | D345: Jose Luis | E345: Nomina Semanal 13 | F345: 3860 | G345: 3860 | H345: =MAX(F345-G345,0) -> 0
A346: Operación | B346: Cuadrillas Siembra | C346: 07/10/2025 | D346: Jose Cargadores | E346: Cuadrilla Cargadores 45 | F346: 31777.75 | G346: 31777.75 | H346: =MAX(F346-G346,0) -> 0
A347: Operación | B347: Cuadrillas Siembra | C347: 17/10/2025 | D347: Jose Cargadores | E347: Cuadrilla Cargadores 42 | F347: 40391 | G347: 40391 | H347: =MAX(F347-G347,0) -> 0
A348: Operación | B348: Cuadrillas Siembra | C348: 24/10/2025 | D348: Jose Cargadores | E348: Cuadrilla Cargadores 43 | F348: 27300 | G348: 27300 | H348: =MAX(F348-G348,0) -> 0
A349: Operación | B349: Cuadrillas Siembra | C349: 31/10/2025 | D349: Jose Cargadores | E349: Cuadrilla Cargadores 44 | F349: 73501.3 | G349: 73501.3 | H349: =MAX(F349-G349,0) -> 0
A350: Operación | B350: Refacciones Maquinaria | C350: 05/08/2025 | D350: JORGE LUIS CASTELLANOS LUNA | E350: AFLOJA TODO | F350: 270 | G350: 270 | H350: =MAX(F350-G350,0) -> 0
A351: Operación | B351: Otros Gastos | C351: 10/02/2026 | D351: JORGE LUIS CASTELLANOS LUNA | E351: VARIOS | F351: 339.9 | G351: 339.9 | H351: =MAX(F351-G351,0) -> 0
...

Sheet 📉 Gráficos
B2: 📉 DASHBOARD DE GRÁFICOS — PROYECTO AGRÍCOLA DE PAPA | P2: Estatus | Q2: Monto
B3: Todos los gráficos se actualizan automáticamente al cambiar los datos. Fuente: hoja "Datos" vía fórmulas SUMIFS. | P3: Ya Pagado | Q3: =SUMIFS(Datos!$G$2:$G$5001,Datos!$A$2:$A$5001,"<>"&Config!$C$9) -> 21136495
P4: Pendiente | Q4: =SUMIFS(Datos!$H$2:$H$5001,Datos!$A$2:$A$5001,"<>"&Config!$C$9) -> 1429255.1
B5: 📊 GRÁFICO 1 — Distribución del Gasto por Área | F5: 💰 GRÁFICO 2 — Estatus de Pagos: Pagado vs Pendiente
P7: Pendiente | Q7: Categoría
P8: =IFERROR(LARGE('🗂️ Por Categoría'!$F$5:$F$40,1),0) -> 1424883.2 | Q8: {=IFERROR(INDEX('🗂️ Por Categoría'!$C$5:$C$40,MATCH(P8,'🗂️ Por Categoría'!$F$5:$F$40,0)),"")} -> Fertilizantes y Agroquimicos
P9: =IFERROR(LARGE('🗂️ Por Categoría'!$F$5:$F$40,2),0) -> 4371.92 | Q9: {=IFERROR(INDEX('🗂️ Por Categoría'!$C$5:$C$40,MATCH(P9,'🗂️ Por Categoría'!$F$5:$F$40,0)),"")} -> Analisis
P10: =IFERROR(LARGE('🗂️ Por Categoría'!$F$5:$F$40,3),0) -> 0 | Q10: {=IFERROR(INDEX('🗂️ Por Categoría'!$C$5:$C$40,MATCH(P10,'🗂️ Por Categoría'!$F$5:$F$40,0)),"")} -> Nomina Administrativa
P11: =IFERROR(LARGE('🗂️ Por Categoría'!$F$5:$F$40,4),0) -> 0 | Q11: {=IFERROR(INDEX('🗂️ Por Categoría'!$C$5:$C$40,MATCH(P11,'🗂️ Por Categoría'!$F$5:$F$40,0)),"")} -> Nomina Administrativa
P12: =IFERROR(LARGE('🗂️ Por Categoría'!$F$5:$F$40,5),0) -> 0 | Q12: {=IFERROR(INDEX('🗂️ Por Categoría'!$C$5:$C$40,MATCH(P12,'🗂️ Por Categoría'!$F$5:$F$40,0)),"")} -> Nomina Administrativa
P13: =IFERROR(LARGE('🗂️ Por Categoría'!$F$5:$F$40,6),0) -> 0 | Q13: {=IFERROR(INDEX('🗂️ Por Categoría'!$C$5:$C$40,MATCH(P13,'🗂️ Por Categoría'!$F$5:$F$40,0)),"")} -> Nomina Administrativa
P17: Área | Q17: Importe
P18: ='📊 Resumen Ejecutivo'!B13 -> Administracion | Q18: ='📊 Resumen Ejecutivo'!D13 -> 1214203.4
P19: ='📊 Resumen Ejecutivo'!B14 -> Operación | Q19: ='📊 Resumen Ejecutivo'!D14 -> 21347717
B30: 🏆 GRÁFICO 3 — Top 10 Categorías de Gasto (mayor a menor)
B31: 💡 El ranking se recalcula automáticamente — si cambian los montos, el orden se actualiza solo.
B56: 📊 GRÁFICO 4 — Pagado vs Pendiente por Categoría (Top 10)
B57: 💡 Verde = ya liquidado. Naranja = aún pendiente de pago. Categorías sin barra naranja están 100% pagadas.
B82: ⚠️ GRÁFICO 5 — Rubros con Pagos Pendientes (ordenados por monto)
B83: 💡 Solo se muestran las categorías que tienen adeudo activo. Si un rubro se liquida, desaparece automáticamente del gráfico.

Sheet 📊 Resumen Ejecutivo
B2: 🌱 PROYECTO AGRÍCOLA DE PAPA — REPORTE FINANCIERO
B3: ="Proyecto: "&Config!C5&" | "&Config!C7&" Hectáreas | Excluye: "&Config!C9 -> Proyecto: Proyecto Papa 2025-2026 | 90 Hectáreas | Excluye: Inversiones
B5: GASTO TOTAL (Op+Adm) | C5: TOTAL PAGADO | D5: PENDIENTE DE PAGO | E5: COSTO / HECTÁREA | F5: GASTOS OPERATIVOS
B6: =SUMIFS(Datos!$F$2:$F$5001,Datos!$A$2:$A$5001,"<>"&Config!$C$9) -> 22561921 | C6: =SUMIFS(Datos!$G$2:$G$5001,Datos!$A$2:$A$5001,"<>"&Config!$C$9) -> 21136495 | D6: =SUMIFS(Datos!$H$2:$H$5001,Datos!$A$2:$A$5001,"<>"&Config!$C$9) -> 1429255.1 | E6: =IFERROR(SUMIFS(Datos!$F$2:$F$5001,Datos!$A$2:$A$5001,"<>"&Config!$C$9)/Config!$C$7,"N/A") -> 250688.01 | F6: =IFERROR(SUMIFS(Datos!$F$2:$F$5001,Datos!$A$2:$A$5001,"Operación"),0) -> 21347717
B7: Ya pagado + pendiente de pago | C7: =IFERROR(TEXT(SUMIFS(Datos!$G$2:$G$5001,Datos!$A$2:$A$5001,"<>"&Config!$C$9)/SUMIFS(Datos!$F$2:$F$5001,Datos!$A$2:$A$5001,"<>"&Config!$C$9),"0.0%")&" del total liquidado","") -> 93,7% del total liquidado | D7: =IFERROR(TEXT(SUMIFS(Datos!$H$2:$H$5001,Datos!$A$2:$A$5001,"<>"&Config!$C$9)/SUMIFS(Datos!$F$2:$F$5001,Datos!$A$2:$A$5001,"<>"&Config!$C$9),"0.0%")&" por liquidar próx. semanas","") -> 6,3% por liquidar próx. semanas | E7: =IFERROR(Config!$C$7&" hectáreas cultivadas","N/A") -> 90 hectáreas cultivadas | F7: "Gastos directos del cultivo"
B11: ¿EN QUÉ SE USÓ EL DINERO? — DESGLOSE POR TIPO DE GASTO
B12: Tipo de Gasto | C12: Descripción | D12: Total Invertido | E12: Total Pagado | F12: Pendiente de Pago | G12: % del Total
B13: Administracion | C13: 🏢 Nómina administrativa, oficina y gastos generales | D13: =SUMIFS(Datos!$F$2:$F$5001,Datos!$A$2:$A$5001,B13) -> 1214203.4 | E13: =SUMIFS(Datos!$G$2:$G$5001,Datos!$A$2:$A$5001,B13) -> 1214203.4 | F13: =SUMIFS(Datos!$H$2:$H$5001,Datos!$A$2:$A$5001,B13) -> 0 | G13: =IFERROR(D13/SUMIFS(Datos!$F$2:$F$5001,Datos!$A$2:$A$5001,"<>"&Config!$C$9),0) -> 0.053816491
B14: Operación | C14: 🌿 Producción, insumos, mano de obra y operación del cultivo | D14: =SUMIFS(Datos!$F$2:$F$5001,Datos!$A$2:$A$5001,B14) -> 21347717 | E14: =SUMIFS(Datos!$G$2:$G$5001,Datos!$A$2:$A$5001,B14) -> 19922292 | F14: =SUMIFS(Datos!$H$2:$H$5001,Datos!$A$2:$A$5001,B14) -> 1429255.1 | G14: =IFERROR(D14/SUMIFS(Datos!$F$2:$F$5001,Datos!$A$2:$A$5001,"<>"&Config!$C$9),0) -> 0.94618351
B15: TOTAL GENERAL | D15: =SUMIFS(Datos!$F$2:$F$5001,Datos!$A$2:$A$5001,"<>"&Config!$C$9) -> 22561921 | E15: =SUMIFS(Datos!$G$2:$G$5001,Datos!$A$2:$A$5001,"<>"&Config!$C$9) -> 21136495 | F15: =SUMIFS(Datos!$H$2:$H$5001,Datos!$A$2:$A$5001,"<>"&Config!$C$9) -> 1429255.1 | G15: =1 -> 1
B17: 💡 GUÍA: Celdas en amarillo son editables. Los totales se calculan automáticamente con fórmulas SUMIFS desde la hoja "Datos". Naranja = monto pendiente de pago.

Sheet 🗂️ Por Categoría
B2: 🗂️ GASTO POR CATEGORÍA (SIN INVERSIONES) — BASE DE CÁLCULO
B3: Para agregar una categoría nueva: inserta una fila y escribe el nombre exacto en col C — las fórmulas SUMIFS calculan automáticamente desde "Datos"
B4: Área | C4: Categoría | D4: Total Invertido | E4: Total Pagado | F4: Pendiente | G4: % del Total
B5: Administracion | C5: Nomina Administrativa | D5: =IFERROR(SUMIFS(Datos!$F$2:$F$5001,Datos!$B$2:$B$5001,C5,Datos!$A$2:$A$5001,"<>"&Config!$C$9),0) -> 547395.66 | E5: =IFERROR(SUMIFS(Datos!$G$2:$G$5001,Datos!$B$2:$B$5001,C5,Datos!$A$2:$A$5001,"<>"&Config!$C$9),0) -> 547395.66 | F5: =IFERROR(SUMIFS(Datos!$H$2:$H$5001,Datos!$B$2:$B$5001,C5,Datos!$A$2:$A$5001,"<>"&Config!$C$9),0) -> 0 | G5: =IFERROR(D5/SUMIFS(Datos!$F$2:$F$5001,Datos!$A$2:$A$5001,"<>"&Config!$C$9),0) -> 0.024261927
B6: Administracion | C6: IMSS e Infonavit | D6: =IFERROR(SUMIFS(Datos!$F$2:$F$5001,Datos!$B$2:$B$5001,C6,Datos!$A$2:$A$5001,"<>"&Config!$C$9),0) -> 463649.63 | E6: =IFERROR(SUMIFS(Datos!$G$2:$G$5001,Datos!$B$2:$B$5001,C6,Datos!$A$2:$A$5001,"<>"&Config!$C$9),0) -> 463649.63 | F6: =IFERROR(SUMIFS(Datos!$H$2:$H$5001,Datos!$B$2:$B$5001,C6,Datos!$A$2:$A$5001,"<>"&Config!$C$9),0) -> 0 | G6: =IFERROR(D6/SUMIFS(Datos!$F$2:$F$5001,Datos!$A$2:$A$5001,"<>"&Config!$C$9),0) -> 0.020550096
B7: Administracion | C7: Honorarios | D7: =IFERROR(SUMIFS(Datos!$F$2:$F$5001,Datos!$B$2:$B$5001,C7,Datos!$A$2:$A$5001,"<>"&Config!$C$9),0) -> 93060.01 | E7: =IFERROR(SUMIFS(Datos!$G$2:$G$5001,Datos!$B$2:$B$5001,C7,Datos!$A$2:$A$5001,"<>"&Config!$C$9),0) -> 93060.01 | F7: =IFERROR(SUMIFS(Datos!$H$2:$H$5001,Datos!$B$2:$B$5001,C7,Datos!$A$2:$A$5001,"<>"&Config!$C$9),0) -> 0 | G7: =IFERROR(D7/SUMIFS(Datos!$F$2:$F$5001,Datos!$A$2:$A$5001,"<>"&Config!$C$9),0) -> 0.0041246493
B8: Administracion | C8: Gastos de Oficina | D8: =IFERROR(SUMIFS(Datos!$F$2:$F$5001,Datos!$B$2:$B$5001,C8,Datos!$A$2:$A$5001,"<>"&Config!$C$9),0) -> 74808.13 | E8: =IFERROR(SUMIFS(Datos!$G$2:$G$5001,Datos!$B$2:$B$5001,C8,Datos!$A$2:$A$5001,"<>"&Config!$C$9),0) -> 74808.13 | F8: =IFERROR(SUMIFS(Datos!$H$2:$H$5001,Datos!$B$2:$B$5001,C8,Datos!$A$2:$A$5001,"<>"&Config!$C$9),0) -> 0 | G8: =IFERROR(D8/SUMIFS(Datos!$F$2:$F$5001,Datos!$A$2:$A$5001,"<>"&Config!$C$9),0) -> 0.0033156809
B9: Administracion | C9: Practicantes | D9: =IFERROR(SUMIFS(Datos!$F$2:$F$5001,Datos!$B$2:$B$5001,C9,Datos!$A$2:$A$5001,"<>"&Config!$C$9),0) -> 14666.66 | E9: =IFERROR(SUMIFS(Datos!$G$2:$G$5001,Datos!$B$2:$B$5001,C9,Datos!$A$2:$A$5001,"<>"&Config!$C$9),0) -> 14666.66 | F9: =IFERROR(SUMIFS(Datos!$H$2:$H$5001,Datos!$B$2:$B$5001,C9,Datos!$A$2:$A$5001,"<>"&Config!$C$9),0) -> 0 | G9: =IFERROR(D9/SUMIFS(Datos!$F$2:$F$5001,Datos!$A$2:$A$5001,"<>"&Config!$C$9),0) -> 0.00065006257
B10: Administracion | C10: Finiquito | D10: =IFERROR(SUMIFS(Datos!$F$2:$F$5001,Datos!$B$2:$B$5001,C10,Datos!$A$2:$A$5001,"<>"&Config!$C$9),0) -> 9543.32 | E10: =IFERROR(SUMIFS(Datos!$G$2:$G$5001,Datos!$B$2:$B$5001,C10,Datos!$A$2:$A$5001,"<>"&Config!$C$9),0) -> 9543.32 | F10: =IFERROR(SUMIFS(Datos!$H$2:$H$5001,Datos!$B$2:$B$5001,C10,Datos!$A$2:$A$5001,"<>"&Config!$C$9),0) -> 0 | G10: =IFERROR(D10/SUMIFS(Datos!$F$2:$F$5001,Datos!$A$2:$A$5001,"<>"&Config!$C$9),0) -> 0.0004229835
B11: Administracion | C11: Uniformes | D11: =IFERROR(SUMIFS(Datos!$F$2:$F$5001,Datos!$B$2:$B$5001,C11,Datos!$A$2:$A$5001,"<>"&Config!$C$9),0) -> 5199.99 | E11: =IFERROR(SUMIFS(Datos!$G$2:$G$5001,Datos!$B$2:$B$5001,C11,Datos!$A$2:$A$5001,"<>"&Config!$C$9),0) -> 5199.99 | F11: =IFERROR(SUMIFS(Datos!$H$2:$H$5001,Datos!$B$2:$B$5001,C11,Datos!$A$2:$A$5001,"<>"&Config!$C$9),0) -> 0 | G11: =IFERROR(D11/SUMIFS(Datos!$F$2:$F$5001,Datos!$A$2:$A$5001,"<>"&Config!$C$9),0) -> 0.00023047639
B12: Administracion | C12: Diesel | D12: =IFERROR(SUMIFS(Datos!$F$2:$F$5001,Datos!$B$2:$B$5001,C12,Datos!$A$2:$A$5001,"<>"&Config!$C$9),0) -> 5080 | E12: =IFERROR(SUMIFS(Datos!$G$2:$G$5001,Datos!$B$2:$B$5001,C12,Datos!$A$2:$A$5001,"<>"&Config!$C$9),0) -> 5080 | F12: =IFERROR(SUMIFS(Datos!$H$2:$H$5001,Datos!$B$2:$B$5001,C12,Datos!$A$2:$A$5001,"<>"&Config!$C$9),0) -> 0 | G12: =IFERROR(D12/SUMIFS(Datos!$F$2:$F$5001,Datos!$A$2:$A$5001,"<>"&Config!$C$9),0) -> 0.00022515814
B13: Administracion | C13: Gasolina | D13: =IFERROR(SUMIFS(Datos!$F$2:$F$5001,Datos!$B$2:$B$5001,C13,Datos!$A$2:$A$5001,"<>"&Config!$C$9),0) -> 10349.97 | E13: =IFERROR(SUMIFS(Datos!$G$2:$G$5001,Datos!$B$2:$B$5001,C13,Datos!$A$2:$A$5001,"<>"&Config!$C$9),0) -> 10349.97 | F13: =IFERROR(SUMIFS(Datos!$H$2:$H$5001,Datos!$B$2:$B$5001,C13,Datos!$A$2:$A$5001,"<>"&Config!$C$9),0) -> 0 | G13: =IFERROR(D13/SUMIFS(Datos!$F$2:$F$5001,Datos!$A$2:$A$5001,"<>"&Config!$C$9),0) -> 0.00045873621
B14: Operación | C14: Fertilizantes y Agroquimicos | D14: =IFERROR(SUMIFS(Datos!$F$2:$F$5001,Datos!$B$2:$B$5001,C14,Datos!$A$2:$A$5001,"<>"&Config!$C$9),0) -> 7166900 | E14: =IFERROR(SUMIFS(Datos!$G$2:$G$5001,Datos!$B$2:$B$5001,C14,Datos!$A$2:$A$5001,"<>"&Config!$C$9),0) -> 5742286.8 | F14: =IFERROR(SUMIFS(Datos!$H$2:$H$5001,Datos!$B$2:$B$5001,C14,Datos!$A$2:$A$5001,"<>"&Config!$C$9),0) -> 1424883.2 | G14: =IFERROR(D14/SUMIFS(Datos!$F$2:$F$5001,Datos!$A$2:$A$5001,"<>"&Config!$C$9),0) -> 0.31765469
B15: Operación | C15: Semilla | D15: =IFERROR(SUMIFS(Datos!$F$2:$F$5001,Datos!$B$2:$B$5001,C15,Datos!$A$2:$A$5001,"<>"&Config!$C$9),0) -> 3700000 | E15: =IFERROR(SUMIFS(Datos!$G$2:$G$5001,Datos!$B$2:$B$5001,C15,Datos!$A$2:$A$5001,"<>"&Config!$C$9),0) -> 3700000 | F15: =IFERROR(SUMIFS(Datos!$H$2:$H$5001,Datos!$B$2:$B$5001,C15,Datos!$A$2:$A$5001,"<>"&Config!$C$9),0) -> 0 | G15: =IFERROR(D15/SUMIFS(Datos!$F$2:$F$5001,Datos!$A$2:$A$5001,"<>"&Config!$C$9),0) -> 0.16399313
B16: Operación | C16: Cuadrillas Cosecha | D16: =IFERROR(SUMIFS(Datos!$F$2:$F$5001,Datos!$B$2:$B$5001,C16,Datos!$A$2:$A$5001,"<>"&Config!$C$9),0) -> 1824339.6 | E16: =IFERROR(SUMIFS(Datos!$G$2:$G$5001,Datos!$B$2:$B$5001,C16,Datos!$A$2:$A$5001,"<>"&Config!$C$9),0) -> 1824339.6 | F16: =IFERROR(SUMIFS(Datos!$H$2:$H$5001,Datos!$B$2:$B$5001,C16,Datos!$A$2:$A$5001,"<>"&Config!$C$9),0) -> 0 | G16: =IFERROR(D16/SUMIFS(Datos!$F$2:$F$5001,Datos!$A$2:$A$5001,"<>"&Config!$C$9),0) -> 0.080859234
... B40: Operación | C40: Gasolina | D40: =IFERROR(SUMIFS(Datos!$F$2:$F$5001,Datos!$B$2:$B$5001,C40,Datos!$A$2:$A$5001,"<>"&Config!$C$9),0) -> 10349.97 | E40: =IFERROR(SUMIFS(Datos!$G$2:$G$5001,Datos!$B$2:$B$5001,C40,Datos!$A$2:$A$5001,"<>"&Config!$C$9),0) -> 10349.97 | F40: =IFERROR(SUMIFS(Datos!$H$2:$H$5001,Datos!$B$2:$B$5001,C40,Datos!$A$2:$A$5001,"<>"&Config!$C$9),0) -> 0 | G40: =IFERROR(D40/SUMIFS(Datos!$F$2:$F$5001,Datos!$A$2:$A$5001,"<>"&Config!$C$9),0) -> 0.00045873621
B41: TOTAL GENERAL | D41: =SUMIFS(Datos!$F$2:$F$5001,Datos!$A$2:$A$5001,"<>"&Config!$C$9) -> 22561921 | E41: =SUMIFS(Datos!$G$2:$G$5001,Datos!$A$2:$A$5001,"<>"&Config!$C$9) -> 21136495 | F41: =SUMIFS(Datos!$H$2:$H$5001,Datos!$A$2:$A$5001,"<>"&Config!$C$9) -> 1429255.1 | G41: =1 -> 1

Sheet 📈 Top 10 Gastos
B2: 🏆 TOP 10 GASTOS MÁS IMPORTANTES DEL PROYECTO | K2: Categoría (de Por Categoría) | L2: Total SUMIFS | M2: Ranking único
B3: Se actualiza automáticamente con LARGE/INDEX — el ranking cambia solo cuando cambias los datos en "Datos" | K3: Nomina Administrativa | L3: =IFERROR(SUMIFS(Datos!$F$2:$F$5001,Datos!$B$2:$B$5001,K3,Datos!$A$2:$A$5001,"<>"&Config!$C$9),0) -> 547395.66 | M3: =RANK(L3,$L$3:$L$40,0)+COUNTIF($L$3:L3,L3)-1 -> 10
K4: IMSS e Infonavit | L4: =IFERROR(SUMIFS(Datos!$F$2:$F$5001,Datos!$B$2:$B$5001,K4,Datos!$A$2:$A$5001,"<>"&Config!$C$9),0) -> 463649.63 | M4: =RANK(L4,$L$3:$L$40,0)+COUNTIF($L$3:L4,L4)-1 -> 12
B5: # | C5: Categoría de Gasto | D5: Total Invertido | E5: Ya Pagado | F5: Pendiente de Pago | G5: % del Total | K5: Honorarios | L5: =IFERROR(SUMIFS(Datos!$F$2:$F$5001,Datos!$B$2:$B$5001,K5,Datos!$A$2:$A$5001,"<>"&Config!$C$9),0) -> 93060.01 | M5: =RANK(L5,$L$3:$L$40,0)+COUNTIF($L$3:L5,L5)-1 -> 23
B6: 1 | C6: {=IFERROR(INDEX($K$3:$K$40,MATCH(1,$M$3:$M$40,0)),"")} -> Fertilizantes y Agroquimicos | D6: {=IFERROR(INDEX($L$3:$L$40,MATCH(1,$M$3:$M$40,0)),0)} -> 7166900 | E6: =IFERROR(SUMIFS(Datos!$G$2:$G$5001,Datos!$B$2:$B$5001,C6,Datos!$A$2:$A$5001,"<>"&Config!$C$9),0) -> 5742286.8 | F6: =IFERROR(SUMIFS(Datos!$H$2:$H$5001,Datos!$B$2:$B$5001,C6,Datos!$A$2:$A$5001,"<>"&Config!$C$9),0) -> 1424883.2 | G6: =IFERROR(D6/SUMIFS(Datos!$F$2:$F$5001,Datos!$A$2:$A$5001,"<>"&Config!$C$9),0) -> 0.31765469 | K6: Gastos de Oficina | L6: =IFERROR(SUMIFS(Datos!$F$2:$F$5001,Datos!$B$2:$B$5001,K6,Datos!$A$2:$A$5001,"<>"&Config!$C$9),0) -> 74808.13 | M6: =RANK(L6,$L$3:$L$40,0)+COUNTIF($L$3:L6,L6)-1 -> 25
B7: 2 | C7: {=IFERROR(INDEX($K$3:$K$40,MATCH(2,$M$3:$M$40,0)),"")} -> Semilla | D7: {=IFERROR(INDEX($L$3:$L$40,MATCH(2,$M$3:$M$40,0)),0)} -> 3700000 | E7: =IFERROR(SUMIFS(Datos!$G$2:$G$5001,Datos!$B$2:$B$5001,C7,Datos!$A$2:$A$5001,"<>"&Config!$C$9),0) -> 3700000 | F7: =IFERROR(SUMIFS(Datos!$H$2:$H$5001,Datos!$B$2:$B$5001,C7,Datos!$A$2:$A$5001,"<>"&Config!$C$9),0) -> 0 | G7: =IFERROR(D7/SUMIFS(Datos!$F$2:$F$5001,Datos!$A$2:$A$5001,"<>"&Config!$C$9),0) -> 0.16399313 | K7: Refacciones y Servicios Vehiculos | L7: =IFERROR(SUMIFS(Datos!$F$2:$F$5001,Datos!$B$2:$B$5001,K7,Datos!$A$2:$A$5001,"<>"&Config!$C$9),0) -> 118501.77 | M7: =RANK(L7,$L$3:$L$40,0)+COUNTIF($L$3:L7,L7)-1 -> 20
B8: 3 | C8: {=IFERROR(INDEX($K$3:$K$40,MATCH(3,$M$3:$M$40,0)),"")} -> Cuadrillas Cosecha | D8: {=IFERROR(INDEX($L$3:$L$40,MATCH(3,$M$3:$M$40,0)),0)} -> 1824339.6 | E8: =IFERROR(SUMIFS(Datos!$G$2:$G$5001,Datos!$B$2:$B$5001,C8,Datos!$A$2:$A$5001,"<>"&Config!$C$9),0) -> 1824339.6 | F8: =IFERROR(SUMIFS(Datos!$H$2:$H$5001,Datos!$B$2:$B$5001,C8,Datos!$A$2:$A$5001,"<>"&Config!$C$9),0) -> 0 | G8: =IFERROR(D8/SUMIFS(Datos!$F$2:$F$5001,Datos!$A$2:$A$5001,"<>"&Config!$C$9),0) -> 0.080859234 | K8: Practicantes | L8: =IFERROR(SUMIFS(Datos!$F$2:$F$5001,Datos!$B$2:$B$5001,K8,Datos!$A$2:$A$5001,"<>"&Config!$C$9),0) -> 14666.66 | M8: =RANK(L8,$L$3:$L$40,0)+COUNTIF($L$3:L8,L8)-1 -> 30
B9: 4 | C9: {=IFERROR(INDEX($K$3:$K$40,MATCH(4,$M$3:$M$40,0)),"")} -> Renta de Tierras | D9: {=IFERROR(INDEX($L$3:$L$40,MATCH(4,$M$3:$M$40,0)),0)} -> 1800000 | E9: =IFERROR(SUMIFS(Datos!$G$2:$G$5001,Datos!$B$2:$B$5001,C9,Datos!$A$2:$A$5001,"<>"&Config!$C$9),0) -> 1800000 | F9: =IFERROR(SUMIFS(Datos!$H$2:$H$5001,Datos!$B$2:$B$5001,C9,Datos!$A$2:$A$5001,"<>"&Config!$C$9),0) -> 0 | G9: =IFERROR(D9/SUMIFS(Datos!$F$2:$F$5001,Datos!$A$2:$A$5001,"<>"&Config!$C$9),0) -> 0.079780442 | K9: Finiquito | L9: =IFERROR(SUMIFS(Datos!$F$2:$F$5001,Datos!$B$2:$B$5001,K9,Datos!$A$2:$A$5001,"<>"&Config!$C$9),0) -> 9543.32 | M9: =RANK(L9,$L$3:$L$40,0)+COUNTIF($L$3:L9,L9)-1 -> 35
B10: 5 | C10: {=IFERROR(INDEX($K$3:$K$40,MATCH(5,$M$3:$M$40,0)),"")} -> Yarda | D10: {=IFERROR(INDEX($L$3:$L$40,MATCH(5,$M$3:$M$40,0)),0)} -> 1201151.1 | E10: =IFERROR(SUMIFS(Datos!$G$2:$G$5001,Datos!$B$2:$B$5001,C10,Datos!$A$2:$A$5001,"<>"&Config!$C$9),0) -> 1201151.1 | F10: =IFERROR(SUMIFS(Datos!$H$2:$H$5001,Datos!$B$2:$B$5001,C10,Datos!$A$2:$A$5001,"<>"&Config!$C$9),0) -> 0 | G10: =IFERROR(D10/SUMIFS(Datos!$F$2:$F$5001,Datos!$A$2:$A$5001,"<>"&Config!$C$9),0) -> 0.053237982 | K10: Uniformes | L10: =IFERROR(SUMIFS(Datos!$F$2:$F$5001,Datos!$B$2:$B$5001,K10,Datos!$A$2:$A$5001,"<>"&Config!$C$9),0) -> 5199.99 | M10: =RANK(L10,$L$3:$L$40,0)+COUNTIF($L$3:L10,L10)-1 -> 37
B11: 6 | C11: {=IFERROR(INDEX($K$3:$K$40,MATCH(6,$M$3:$M$40,0)),"")} -> Sistema de Riego | D11: {=IFERROR(INDEX($L$3:$L$40,MATCH(6,$M$3:$M$40,0)),0)} -> 965646.31 | E11: =IFERROR(SUMIFS(Datos!$G$2:$G$5001,Datos!$B$2:$B$5001,C11,Datos!$A$2:$A$5001,"<>"&Config!$C$9),0) -> 965646.31 | F11: =IFERROR(SUMIFS(Datos!$H$2:$H$5001,Datos!$B$2:$B$5001,C11,Datos!$A$2:$A$5001,"<>"&Config!$C$9),0) -> 0 | G11: =IFERROR(D11/SUMIFS(Datos!$F$2:$F$5001,Datos!$A$2:$A$5001,"<>"&Config!$C$9),0) -> 0.042799828 | K11: Diesel | L11: =IFERROR(SUMIFS(Datos!$F$2:$F$5001,Datos!$B$2:$B$5001,K11,Datos!$A$2:$A$5001,"<>"&Config!$C$9),0) -> 5080 | M11: =RANK(L11,$L$3:$L$40,0)+COUNTIF($L$3:L11,L11)-1 -> 38
B12: 7 | C12: {=IFERROR(INDEX($K$3:$K$40,MATCH(7,$M$3:$M$40,0)),"")} -> Nomina de Campo | D12: {=IFERROR(INDEX($L$3:$L$40,MATCH(7,$M$3:$M$40,0)),0)} -> 881045.1 | E12: =IFERROR(SUMIFS(Datos!$G$2:$G$5001,Datos!$B$2:$B$5001,C12,Datos!$A$2:$A$5001,"<>"&Config!$C$9),0) -> 884605.1 | F12: =IFERROR(SUMIFS(Datos!$H$2:$H$5001,Datos!$B$2:$B$5001,C12,Datos!$A$2:$A$5001,"<>"&Config!$C$9),0) -> 0 | G12: =IFERROR(D12/SUMIFS(Datos!$F$2:$F$5001,Datos!$A$2:$A$5001,"<>"&Config!$C$9),0) -> 0.039050093 | K12: Gasolina | L12: =IFERROR(SUMIFS(Datos!$F$2:$F$5001,Datos!$B$2:$B$5001,K12,Datos!$A$2:$A$5001,"<>"&Config!$C$9),0) -> 10349.97 | M12: =RANK(L12,$L$3:$L$40,0)+COUNTIF($L$3:L12,L12)-1 -> 33
B13: 8 | C13: {=IFERROR(INDEX($K$3:$K$40,MATCH(8,$M$3:$M$40,0)),"")} -> Fletes | D13: {=IFERROR(INDEX($L$3:$L$40,MATCH(8,$M$3:$M$40,0)),0)} -> 766900.04 | E13: =IFERROR(SUMIFS(Datos!$G$2:$G$5001,Datos!$B$2:$B$5001,C13,Datos!$A$2:$A$5001,"<>"&Config!$C$9),0) -> 766900.04 | F13: =IFERROR(SUMIFS(Datos!$H$2:$H$5001,Datos!$B$2:$B$5001,C13,Datos!$A$2:$A$5001,"<>"&Config!$C$9),0) -> 0 | G13: =IFERROR(D13/SUMIFS(Datos!$F$2:$F$5001,Datos!$A$2:$A$5001,"<>"&Config!$C$9),0) -> 0.033990902 | K13: Fertilizantes y Agroquimicos | L13: =IFERROR(SUMIFS(Datos!$F$2:$F$5001,Datos!$B$2:$B$5001,K13,Datos!$A$2:$A$5001,"<>"&Config!$C$9),0) -> 7166900 | M13: =RANK(L13,$L$3:$L$40,0)+COUNTIF($L$3:L13,L13)-1 -> 1
B14: 9 | C14: {=IFERROR(INDEX($K$3:$K$40,MATCH(9,$M$3:$M$40,0)),"")} -> Nomina Operativa | D14: {=IFERROR(INDEX($L$3:$L$40,MATCH(9,$M$3:$M$40,0)),0)} -> 575219.49 | E14: =IFERROR(SUMIFS(Datos!$G$2:$G$5001,Datos!$B$2:$B$5001,C14,Datos!$A$2:$A$5001,"<>"&Config!$C$9),0) -> 575219.49 | F14: =IFERROR(SUMIFS(Datos!$H$2:$H$5001,Datos!$B$2:$B$5001,C14,Datos!$A$2:$A$5001,"<>"&Config!$C$9),0) -> 0 | G14: =IFERROR(D14/SUMIFS(Datos!$F$2:$F$5001,Datos!$A$2:$A$5001,"<>"&Config!$C$9),0) -> 0.025495147 | K14: Semilla | L14: =IFERROR(SUMIFS(Datos!$F$2:$F$5001,Datos!$B$2:$B$5001,K14,Datos!$A$2:$A$5001,"<>"&Config!$C$9),0) -> 3700000 | M14: =RANK(L14,$L$3:$L$40,0)+COUNTIF($L$3:L14,L14)-1 -> 2
B15: 10 | C15: {=IFERROR(INDEX($K$3:$K$40,MATCH(10,$M$3:$M$40,0)),"")} -> Nomina Administrativa | D15: {=IFERROR(INDEX($L$3:$L$40,MATCH(10,$M$3:$M$40,0)),0)} -> 547395.66 | E15: =IFERROR(SUMIFS(Datos!$G$2:$G$5001,Datos!$B$2:$B$5001,C15,Datos!$A$2:$A$5001,"<>"&Config!$C$9),0) -> 547395.66 | F15: =IFERROR(SUMIFS(Datos!$H$2:$H$5001,Datos!$B$2:$B$5001,C15,Datos!$A$2:$A$5001,"<>"&Config!$C$9),0) -> 0 | G15: =IFERROR(D15/SUMIFS(Datos!$F$2:$F$5001,Datos!$A$2:$A$5001,"<>"&Config!$C$9),0) -> 0.024261927 | K15: Cuadrillas Cosecha | L15: =IFERROR(SUMIFS(Datos!$F$2:$F$5001,Datos!$B$2:$B$5001,K15,Datos!$A$2:$A$5001,"<>"&Config!$C$9),0) -> 1824339.6 | M15: =RANK(L15,$L$3:$L$40,0)+COUNTIF($L$3:L15,L15)-1 -> 3
B16: SUBTOTAL TOP 10 | D16: =SUM(D6:D15) -> 19428597 | E16: =SUM(E6:E15) -> 18007544 | F16: =SUM(F6:F15) -> 1424883.2 | G16: =IFERROR(D16/SUMIFS(Datos!$F$2:$F$5001,Datos!$A$2:$A$5001,"<>"&Config!$C$9),0) -> 0.86112338 | K16: Renta de Tierras | L16: =IFERROR(SUMIFS(Datos!$F$2:$F$5001,Datos!$B$2:$B$5001,K16,Datos!$A$2:$A$5001,"<>"&Config!$C$9),0) -> 1800000 | M16: =RANK(L16,$L$3:$L$40,0)+COUNTIF($L$3:L16,L16)-1 -> 4
K17: Yarda | L17: =IFERROR(SUMIFS(Datos!$F$2:$F$5001,Datos!$B$2:$B$5001,K17,Datos!$A$2:$A$5001,"<>"&Config!$C$9),0) -> 1201151.1 | M17: =RANK(L17,$L$3:$L$40,0)+COUNTIF($L$3:L17,L17)-1 -> 5
B18: ✅ El ranking se recalcula automáticamente. La columna oculta de ayuda (K-M) calcula los totales por categoría. Si hay empate exacto en montos, el orden puede variar. | K18: Sistema de Riego | L18: =IFERROR(SUMIFS(Datos!$F$2:$F$5001,Datos!$B$2:$B$5001,K18,Datos!$A$2:$A$5001,"<>"&Config!$C$9),0) -> 965646.31 | M18: =RANK(L18,$L$3:$L$40,0)+COUNTIF($L$3:L18,L18)-1 -> 6
K19: Nomina de Campo | L19: =IFERROR(SUMIFS(Datos!$F$2:$F$5001,Datos!$B$2:$B$5001,K19,Datos!$A$2:$A$5001,"<>"&Config!$C$9),0) -> 881045.1 | M19: =RANK(L19,$L$3:$L$40,0)+COUNTIF($L$3:L19,L19)-1 -> 7
K20: Nomina Operativa | L20: =IFERROR(SUMIFS(Datos!$F$2:$F$5001,Datos!$B$2:$B$5001,K20,Datos!$A$2:$A$5001,"<>"&Config!$C$9),0) -> 575219.49 | M20: =RANK(L20,$L$3:$L$40,0)+COUNTIF($L$3:L20,L20)-1 -> 9
K21: Fletes | L21: =IFERROR(SUMIFS(Datos!$F$2:$F$5001,Datos!$B$2:$B$5001,K21,Datos!$A$2:$A$5001,"<>"&Config!$C$9),0) -> 766900.04 | M21: =RANK(L21,$L$3:$L$40,0)+COUNTIF($L$3:L21,L21)-1 -> 8
K22: Cuadrillas Siembra | L22: =IFERROR(SUMIFS(Datos!$F$2:$F$5001,Datos!$B$2:$B$5001,K22,Datos!$A$2:$A$5001,"<>"&Config!$C$9),0) -> 506563.84 | M22: =RANK(L22,$L$3:$L$40,0)+COUNTIF($L$3:L22,L22)-1 -> 11
K23: Conduccion de Agua | L23: =IFERROR(SUMIFS(Datos!$F$2:$F$5001,Datos!$B$2:$B$5001,K23,Datos!$A$2:$A$5001,"<>"&Config!$C$9),0) -> 419600 | M23: =RANK(L23,$L$3:$L$40,0)+COUNTIF($L$3:L23,L23)-1 -> 14
K24: Fumigacion Aerea | L24: =IFERROR(SUMIFS(Datos!$F$2:$F$5001,Datos!$B$2:$B$5001,K24,Datos!$A$2:$A$5001,"<>"&Config!$C$9),0) -> 266470 | M24: =RANK(L24,$L$3:$L$40,0)+COUNTIF($L$3:L24,L24)-1 -> 15
K25: Refacciones Maquinaria | L25: =IFERROR(SUMIFS(Datos!$F$2:$F$5001,Datos!$B$2:$B$5001,K25,Datos!$A$2:$A$5001,"<>"&Config!$C$9),0) -> 237889.29 | M25: =RANK(L25,$L$3:$L$40,0)+COUNTIF($L$3:L25,L25)-1 -> 16
K26: Cuadrillas Deshierbe | L26: =IFERROR(SUMIFS(Datos!$F$2:$F$5001,Datos!$B$2:$B$5001,K26,Datos!$A$2:$A$5001,"<>"&Config!$C$9),0) -> 192700 | M26: =RANK(L26,$L$3:$L$40,0)+COUNTIF($L$3:L26,L26)-1 -> 17
K27: Asesoria | L27: =IFERROR(SUMIFS(Datos!$F$2:$F$5001,Datos!$B$2:$B$5001,K27,Datos!$A$2:$A$5001,"<>"&Config!$C$9),0) -> 185894.5 | M27: =RANK(L27,$L$3:$L$40,0)+COUNTIF($L$3:L27,L27)-1 -> 18
K28: Otros Gastos | L28: =IFERROR(SUMIFS(Datos!$F$2:$F$5001,Datos!$B$2:$B$5001,K28,Datos!$A$2:$A$5001,"<>"&Config!$C$9),0) -> 155218.6 | M28: =RANK(L28,$L$3:$L$40,0)+COUNTIF($L$3:L28,L28)-1 -> 19
K29: Liquidacion | L29: =IFERROR(SUMIFS(Datos!$F$2:$F$5001,Datos!$B$2:$B$5001,K29,Datos!$A$2:$A$5001,"<>"&Config!$C$9),0) -> 111785.52 | M29: =RANK(L29,$L$3:$L$40,0)+COUNTIF($L$3:L29,L29)-1 -> 22
K30: Cosecha | L30: =IFERROR(SUMIFS(Datos!$F$2:$F$5001,Datos!$B$2:$B$5001,K30,Datos!$A$2:$A$5001,"<>"&Config!$C$9),0) -> 86856.23 | M30: =RANK(L30,$L$3:$L$40,0)+COUNTIF($L$3:L30,L30)-1 -> 24
... K40: IMSS e Infonavit | L40: =IFERROR(SUMIFS(Datos!$F$2:$F$5001,Datos!$B$2:$B$5001,K40,Datos!$A$2:$A$5001,"<>"&Config!$C$9),0) -> 463649.63 | M40: =RANK(L40,$L$3:$L$40,0)+COUNTIF($L$3:L40,L40)-1 -> 13

Sheet ⚠️ Pendiente por Pagar
B2: ⚠️ PAGOS PENDIENTES — COMPROMISOS A LIQUIDAR
B3: ="Total pendiente: $"&TEXT(SUMIFS(Datos!$H$2:$H$5001,Datos!$A$2:$A$5001,"<>"&Config!$C$9),"#,##0.00")&" | Filtra columna Pendiente > 0 para ver sólo rubros con adeudo" -> Total pendiente: $1.429.255,12 | Filtra columna Pendiente > 0 para ver sólo rubros con adeudo
C5: TOTAL PENDIENTE | E5: TOTAL YA PAGADO | G5: TRANSACCIONES
C6: =SUMIFS(Datos!$H$2:$H$5001,Datos!$A$2:$A$5001,"<>"&Config!$C$9) -> 1429255.1 | E6: =SUMIFS(Datos!$G$2:$G$5001,Datos!$A$2:$A$5001,"<>"&Config!$C$9) -> 21136495 | G6: =COUNTIF(Datos!$H$2:$H$5001,">0") -> 30
C7: Monto comprometido sin pagar | E7: Del gasto operativo/administrativo | G7: Con saldo pendiente de pago
B9: Área | C9: Categoría | D9: Total Invertido | E9: Total Pagado | F9: Pendiente | G9: % Pendiente/Total
B10: Administracion | C10: Nomina Administrativa | D10: =IFERROR(SUMIFS(Datos!$F$2:$F$5001,Datos!$B$2:$B$5001,C10,Datos!$A$2:$A$5001,"<>"&Config!$C$9),0) -> 547395.66 | E10: =IFERROR(SUMIFS(Datos!$G$2:$G$5001,Datos!$B$2:$B$5001,C10,Datos!$A$2:$A$5001,"<>"&Config!$C$9),0) -> 547395.66 | F10: =IFERROR(SUMIFS(Datos!$H$2:$H$5001,Datos!$B$2:$B$5001,C10,Datos!$A$2:$A$5001,"<>"&Config!$C$9),0) -> 0 | G10: =IFERROR(F10/SUMIFS(Datos!$F$2:$F$5001,Datos!$A$2:$A$5001,"<>"&Config!$C$9),0) -> 0
B11: Administracion | C11: IMSS e Infonavit | D11: =IFERROR(SUMIFS(Datos!$F$2:$F$5001,Datos!$B$2:$B$5001,C11,Datos!$A$2:$A$5001,"<>"&Config!$C$9),0) -> 463649.63 | E11: =IFERROR(SUMIFS(Datos!$G$2:$G$5001,Datos!$B$2:$B$5001,C11,Datos!$A$2:$A$5001,"<>"&Config!$C$9),0) -> 463649.63 | F11: =IFERROR(SUMIFS(Datos!$H$2:$H$5001,Datos!$B$2:$B$5001,C11,Datos!$A$2:$A$5001,"<>"&Config!$C$9),0) -> 0 | G11: =IFERROR(F11/SUMIFS(Datos!$F$2:$F$5001,Datos!$A$2:$A$5001,"<>"&Config!$C$9),0) -> 0
B12: Administracion | C12: Honorarios | D12: =IFERROR(SUMIFS(Datos!$F$2:$F$5001,Datos!$B$2:$B$5001,C12,Datos!$A$2:$A$5001,"<>"&Config!$C$9),0) -> 93060.01 | E12: =IFERROR(SUMIFS(Datos!$G$2:$G$5001,Datos!$B$2:$B$5001,C12,Datos!$A$2:$A$5001,"<>"&Config!$C$9),0) -> 93060.01 | F12: =IFERROR(SUMIFS(Datos!$H$2:$H$5001,Datos!$B$2:$B$5001,C12,Datos!$A$2:$A$5001,"<>"&Config!$C$9),0) -> 0 | G12: =IFERROR(F12/SUMIFS(Datos!$F$2:$F$5001,Datos!$A$2:$A$5001,"<>"&Config!$C$9),0) -> 0
B13: Administracion | C13: Gastos de Oficina | D13: =IFERROR(SUMIFS(Datos!$F$2:$F$5001,Datos!$B$2:$B$5001,C13,Datos!$A$2:$A$5001,"<>"&Config!$C$9),0) -> 74808.13 | E13: =IFERROR(SUMIFS(Datos!$G$2:$G$5001,Datos!$B$2:$B$5001,C13,Datos!$A$2:$A$5001,"<>"&Config!$C$9),0) -> 74808.13 | F13: =IFERROR(SUMIFS(Datos!$H$2:$H$5001,Datos!$B$2:$B$5001,C13,Datos!$A$2:$A$5001,"<>"&Config!$C$9),0) -> 0 | G13: =IFERROR(F13/SUMIFS(Datos!$F$2:$F$5001,Datos!$A$2:$A$5001,"<>"&Config!$C$9),0) -> 0
B14: Administracion | C14: Refacciones y Servicios Vehiculos | D14: =IFERROR(SUMIFS(Datos!$F$2:$F$5001,Datos!$B$2:$B$5001,C14,Datos!$A$2:$A$5001,"<>"&Config!$C$9),0) -> 118501.77 | E14: =IFERROR(SUMIFS(Datos!$G$2:$G$5001,Datos!$B$2:$B$5001,C14,Datos!$A$2:$A$5001,"<>"&Config!$C$9),0) -> 118501.77 | F14: =IFERROR(SUMIFS(Datos!$H$2:$H$5001,Datos!$B$2:$B$5001,C14,Datos!$A$2:$A$5001,"<>"&Config!$C$9),0) -> 0 | G14: =IFERROR(F14/SUMIFS(Datos!$F$2:$F$5001,Datos!$A$2:$A$5001,"<>"&Config!$C$9),0) -> 0
B15: Administracion | C15: Practicantes | D15: =IFERROR(SUMIFS(Datos!$F$2:$F$5001,Datos!$B$2:$B$5001,C15,Datos!$A$2:$A$5001,"<>"&Config!$C$9),0) -> 14666.66 | E15: =IFERROR(SUMIFS(Datos!$G$2:$G$5001,Datos!$B$2:$B$5001,C15,Datos!$A$2:$A$5001,"<>"&Config!$C$9),0) -> 14666.66 | F15: =IFERROR(SUMIFS(Datos!$H$2:$H$5001,Datos!$B$2:$B$5001,C15,Datos!$A$2:$A$5001,"<>"&Config!$C$9),0) -> 0 | G15: =IFERROR(F15/SUMIFS(Datos!$F$2:$F$5001,Datos!$A$2:$A$5001,"<>"&Config!$C$9),0) -> 0
B16: Administracion | C16: Finiquito | D16: =IFERROR(SUMIFS(Datos!$F$2:$F$5001,Datos!$B$2:$B$5001,C16,Datos!$A$2:$A$5001,"<>"&Config!$C$9),0) -> 9543.32 | E16: =IFERROR(SUMIFS(Datos!$G$2:$G$5001,Datos!$B$2:$B$5001,C16,Datos!$A$2:$A$5001,"<>"&Config!$C$9),0) -> 9543.32 | F16: =IFERROR(SUMIFS(Datos!$H$2:$H$5001,Datos!$B$2:$B$5001,C16,Datos!$A$2:$A$5001,"<>"&Config!$C$9),0) -> 0 | G16: =IFERROR(F16/SUMIFS(Datos!$F$2:$F$5001,Datos!$A$2:$A$5001,"<>"&Config!$C$9),0) -> 0
B17: Administracion | C17: Uniformes | D17: =IFERROR(SUMIFS(Datos!$F$2:$F$5001,Datos!$B$2:$B$5001,C17,Datos!$A$2:$A$5001,"<>"&Config!$C$9),0) -> 5199.99 | E17: =IFERROR(SUMIFS(Datos!$G$2:$G$5001,Datos!$B$2:$B$5001,C17,Datos!$A$2:$A$5001,"<>"&Config!$C$9),0) -> 5199.99 | F17: =IFERROR(SUMIFS(Datos!$H$2:$H$5001,Datos!$B$2:$B$5001,C17,Datos!$A$2:$A$5001,"<>"&Config!$C$9),0) -> 0 | G17: =IFERROR(F17/SUMIFS(Datos!$F$2:$F$5001,Datos!$A$2:$A$5001,"<>"&Config!$C$9),0) -> 0
B18: Administracion | C18: Diesel | D18: =IFERROR(SUMIFS(Datos!$F$2:$F$5001,Datos!$B$2:$B$5001,C18,Datos!$A$2:$A$5001,"<>"&Config!$C$9),0) -> 5080 | E18: =IFERROR(SUMIFS(Datos!$G$2:$G$5001,Datos!$B$2:$B$5001,C18,Datos!$A$2:$A$5001,"<>"&Config!$C$9),0) -> 5080 | F18: =IFERROR(SUMIFS(Datos!$H$2:$H$5001,Datos!$B$2:$B$5001,C18,Datos!$A$2:$A$5001,"<>"&Config!$C$9),0) -> 0 | G18: =IFERROR(F18/SUMIFS(Datos!$F$2:$F$5001,Datos!$A$2:$A$5001,"<>"&Config!$C$9),0) -> 0
B19: Administracion | C19: Gasolina | D19: =IFERROR(SUMIFS(Datos!$F$2:$F$5001,Datos!$B$2:$B$5001,C19,Datos!$A$2:$A$5001,"<>"&Config!$C$9),0) -> 10349.97 | E19: =IFERROR(SUMIFS(Datos!$G$2:$G$5001,Datos!$B$2:$B$5001,C19,Datos!$A$2:$A$5001,"<>"&Config!$C$9),0) -> 10349.97 | F19: =IFERROR(SUMIFS(Datos!$H$2:$H$5001,Datos!$B$2:$B$5001,C19,Datos!$A$2:$A$5001,"<>"&Config!$C$9),0) -> 0 | G19: =IFERROR(F19/SUMIFS(Datos!$F$2:$F$5001,Datos!$A$2:$A$5001,"<>"&Config!$C$9),0) -> 0
B20: Operación | C20: Fertilizantes y Agroquimicos | D20: =IFERROR(SUMIFS(Datos!$F$2:$F$5001,Datos!$B$2:$B$5001,C20,Datos!$A$2:$A$5001,"<>"&Config!$C$9),0) -> 7166900 | E20: =IFERROR(SUMIFS(Datos!$G$2:$G$5001,Datos!$B$2:$B$5001,C20,Datos!$A$2:$A$5001,"<>"&Config!$C$9),0) -> 5742286.8 | F20: =IFERROR(SUMIFS(Datos!$H$2:$H$5001,Datos!$B$2:$B$5001,C20,Datos!$A$2:$A$5001,"<>"&Config!$C$9),0) -> 1424883.2 | G20: =IFERROR(F20/SUMIFS(Datos!$F$2:$F$5001,Datos!$A$2:$A$5001,"<>"&Config!$C$9),0) -> 0.06315434
B21: Operación | C21: Semilla | D21: =IFERROR(SUMIFS(Datos!$F$2:$F$5001,Datos!$B$2:$B$5001,C21,Datos!$A$2:$A$5001,"<>"&Config!$C$9),0) -> 3700000 | E21: =IFERROR(SUMIFS(Datos!$G$2:$G$5001,Datos!$B$2:$B$5001,C21,Datos!$A$2:$A$5001,"<>"&Config!$C$9),0) -> 3700000 | F21: =IFERROR(SUMIFS(Datos!$H$2:$H$5001,Datos!$B$2:$B$5001,C21,Datos!$A$2:$A$5001,"<>"&Config!$C$9),0) -> 0 | G21: =IFERROR(F21/SUMIFS(Datos!$F$2:$F$5001,Datos!$A$2:$A$5001,"<>"&Config!$C$9),0) -> 0
... B47: Operación | C47: IMSS e Infonavit | D47: =IFERROR(SUMIFS(Datos!$F$2:$F$5001,Datos!$B$2:$B$5001,C47,Datos!$A$2:$A$5001,"<>"&Config!$C$9),0) -> 463649.63 | E47: =IFERROR(SUMIFS(Datos!$G$2:$G$5001,Datos!$B$2:$B$5001,C47,Datos!$A$2:$A$5001,"<>"&Config!$C$9),0) -> 463649.63 | F47: =IFERROR(SUMIFS(Datos!$H$2:$H$5001,Datos!$B$2:$B$5001,C47,Datos!$A$2:$A$5001,"<>"&Config!$C$9),0) -> 0 | G47: =IFERROR(F47/SUMIFS(Datos!$F$2:$F$5001,Datos!$A$2:$A$5001,"<>"&Config!$C$9),0) -> 0
B48: TOTAL PENDIENTE | D48: =SUMIFS(Datos!$F$2:$F$5001,Datos!$A$2:$A$5001,"<>"&Config!$C$9) -> 22561921 | E48: =SUMIFS(Datos!$G$2:$G$5001,Datos!$A$2:$A$5001,"<>"&Config!$C$9) -> 21136495 | F48: =SUMIFS(Datos!$H$2:$H$5001,Datos!$A$2:$A$5001,"<>"&Config!$C$9) -> 1429255.1 | G48: =IFERROR(F48/D48,0) -> 0.063348114
B50: 💡 USA EL FILTRO: Haz clic en ▼ de la columna "Pendiente" → Filtros de número → Mayor que → 0 para ver sólo los rubros con adeudo activo. Todos los valores se actualizan solos al cambiar los datos.

Sheet 🏭 Deuda Bodegas → Agrícola
B2: 🏭 DEUDA DE BODEGAS CON AGRÍCOLA
B3: Gastos que el negocio de Bodegas generó y que la Agrícola cubrió — pendientes de reembolso
B5: TOTAL ADEUDADO | D5: EXCLUIDO | E5: ESTATUS
B6: =SUM(E11:E22) -> 617269.53 | D6: BOLSA FISCAL MA | E6: 4 conceptos
B7: Monto que Bodegas debe a Agrícola | D7: $800,000.00 — No forma parte del adeudo | E7: ⏳ Pendiente de reembolso
B10: Fecha | C10: Concepto / Proveedor | D10: Descripción | E10: Importe
B11: 06/02/2026 | C11: ROGELIO ESTRADA | D11: Pago a proveedor / mano de obra
B12: 06/02/2026 | C12: RAMICO | D12: Proveedor materiales y servicios
B13: 27/02/2026 | C13: KN MATERIALES BODEGA | D13: Materiales para bodega
B14: 22/02/2026 | C14: SERVICIOS DE EQ DE REFRIGERACION | D14: Servicios equipo de refrigeración
B15: 01/03/2026 | C15: MENSUALIDAD CAT | D15: Mensualidad CAT (marzo) | E15: 107862.86
B16: 13/03/2026 | C16: MATERIAL BODEGAS | D16: Material para bodegas
B17: 20/03/2026 | C17: ISMAEL ELECTRICO BODEGAS | D17: Servicios eléctricos en bodegas
B18: 20/03/2026 | C18: PINTURA Y SELLADOR OSEL | D18: Pintura y sellador
B19: 27/03/2026 | C19: SELLADOR PARA PISO BODEGA 5 | D19: Sellador para piso bodega 5
B20: 01/04/2026 | C20: MENSUALIDAD CAT | D20: Mensualidad CAT (abril) | E20: 107862.86
B21: 13/04/2026 | C21: POLIZA DE SEGUROS BODEGAS | D21: Póliza de seguros bodegas | E21: 218643.81
C22: NOMINAS OPERATIVAS | D22: Nóminas del personal operativo | E22: 182900
B23: TOTAL ADEUDADO — BODEGAS A AGRÍCOLA | E23: =SUM(E11:E22) -> 617269.53
B25: ⚠️ CONCEPTO EXCLUIDO: "PAGO ROGELIO ESTRADA MANO DE OBRA" $800,000.00 — Pertenece a BOLSA FISCAL MA y NO es parte del adeudo de Bodegas con Agrícola. El total bruto de la relación era $4,561,458.36; el adeudo real es el SUM de la tabla (E11:E22).
B27: 📋 INSTRUCCIONES: Las celdas en amarillo (columna E) son editables. Agrega o elimina filas entre los datos y el total — actualiza la fórmula SUM en el total para incluir las nuevas filas. El total de la tarjeta superior (B6) se recalcula automáticamente.
